markdownify_mcp/__init__.py
markdownify_mcp/server.py
markdownify_mcp_server-0.1.13.dist-info/METADATA
markdownify_mcp_server-0.1.13.dist-info/WHEEL
markdownify_mcp_server-0.1.13.dist-info/entry_points.txt
markdownify_mcp_server-0.1.13.dist-info/top_level.txt
markdownify_mcp_server-0.1.13.dist-info/RECORD
