Metadata-Version: 2.4
Name: markdownify-mcp-server
Version: 0.1.13
Summary: Add your description here
Requires-Python: >=3.13
Requires-Dist: markitdown[all,pdf,xlsx]>=0.1.1
Requires-Dist: mcp[cli]>=1.6.0
